wave_view/__init__.py
wave_view/cli.py
wave_view/loader.py
wave_view/py.typed
wave_view/_archive/config_legacy.py
wave_view/_archive/plotspec_v0_2_0.py
wave_view/core/__init__.py
wave_view/core/plotspec.py
wave_view/core/plotting.py
wave_view/core/wavedataset.py
wave_view/utils/__init__.py
wave_view/utils/env.py
wave_view-1.0.1.dist-info/licenses/LICENSE
wave_view-1.0.1.dist-info/METADATA
wave_view-1.0.1.dist-info/WHEEL
wave_view-1.0.1.dist-info/entry_points.txt
wave_view-1.0.1.dist-info/top_level.txt
wave_view-1.0.1.dist-info/RECORD
