Metadata-Version: 2.4
Name: wave_view
Version: 1.0.1
Summary: A Python package for visualizing SPICE simulation waveforms in Jupyter notebooks
Author-email: Jianxun Zhu <jianxun.zhu@example.com>
Maintainer-email: Jianxun Zhu <jianxun.zhu@example.com>
License-Expression: MIT
Project-URL: Homepage, https://github.com/Jianxun/wave_view
Project-URL: Bug Reports, https://github.com/Jianxun/wave_view/issues
Project-URL: Source, https://github.com/Jianxun/wave_view
Project-URL: Documentation, https://github.com/Jianxun/wave_view/tree/main/docs
Keywords: spice,simulation,waveform,visualization,jupyter,eda
Classifier: Development Status :: 5 - Production/Stable
Classifier: Intended Audience :: Developers
Classifier: Intended Audience :: Science/Research
Classifier: Topic :: Scientific/Engineering :: Electronic Design Automation (EDA)
Classifier: Topic :: Software Development :: Libraries :: Python Modules
Classifier: Programming Language :: Python :: 3
Classifier: Programming Language :: Python :: 3.8
Classifier: Programming Language :: Python :: 3.9
Classifier: Programming Language :: Python :: 3.10
Classifier: Programming Language :: Python :: 3.11
Classifier: Programming Language :: Python :: 3.12
Classifier: Framework :: Jupyter
Requires-Python: >=3.8
License-File: LICENSE
Requires-Dist: plotly>=5.0.0
Requires-Dist: numpy>=1.20.0
Requires-Dist: PyYAML>=6.0
Requires-Dist: spicelib>=1.0.0
Requires-Dist: click>=8.0.0
Requires-Dist: pydantic>=2.0.0
Provides-Extra: dev
Requires-Dist: pytest>=7.0.0; extra == "dev"
Requires-Dist: pytest-cov>=4.0.0; extra == "dev"
Requires-Dist: black>=22.0.0; extra == "dev"
Requires-Dist: isort>=5.0.0; extra == "dev"
Requires-Dist: flake8>=4.0.0; extra == "dev"
Requires-Dist: mypy>=1.0.0; extra == "dev"
Requires-Dist: pre-commit>=2.0.0; extra == "dev"
Provides-Extra: docs
Requires-Dist: sphinx>=5.0.0; extra == "docs"
Requires-Dist: sphinx-rtd-theme>=1.0.0; extra == "docs"
Requires-Dist: myst-parser>=0.18.0; extra == "docs"
Provides-Extra: jupyter
Requires-Dist: ipywidgets>=8.0.0; extra == "jupyter"
Requires-Dist: jupyter>=1.0.0; extra == "jupyter"
Requires-Dist: jupyterlab>=3.0.0; extra == "jupyter"
Dynamic: license-file
